canlinkapis/__init__.py
canlinkapis/pycanlink.py
moduleTest/__init__.py
moduleTest/pypitest.py
canlink_apis-1.0.0.3.dist-info/METADATA
canlink_apis-1.0.0.3.dist-info/WHEEL
canlink_apis-1.0.0.3.dist-info/top_level.txt
canlink_apis-1.0.0.3.dist-info/RECORD
